mmir/__init__.py
mmir/types.py
mmir/camera/__init__.py
mmir/camera/camera.py
mmir/examples/__init__.py
mmir/examples/disparity_maps/__init__.py
mmir/examples/disparity_maps/register.py
mmir/examples/vis_to_flir/__init__.py
mmir/examples/vis_to_flir/config.py
mmir/examples/vis_to_flir/register.py
mmir/examples/vis_to_vis/__init__.py
mmir/examples/vis_to_vis/register.py
mmir/feature_detection/__init__.py
mmir/feature_detection/feature_detector.py
mmir/feature_detection/gftt_feature_detector.py
mmir/feature_detection/filters/__init__.py
mmir/feature_detection/filters/descriptor_filter.py
mmir/feature_detection/filters/epipolar_distance_filter.py
mmir/feature_detection/filters/x_position_filter.py
mmir/feature_detection/filters/y_position_filter.py
mmir/feature_matching/__init__.py
mmir/feature_matching/feature_matcher.py
mmir/feature_matching/hog_feature_matcher.py
mmir/feature_matching/mi_feature_matcher.py
mmir/mapping/__init__.py
mmir/mapping/epipolar_transfer.py
mmir/mapping/mapping_estimator.py
mmir/mapping/mapping_visualizer.py
mmir/mapping/polynomial_transform_estimator.py
mmir/mapping/projective_transform_estimator.py
mmir/mapping/ransac_estimator.py
mmir/math/__init__.py
mmir/math/epipolar.py
mmir/math/math.py
mmir/pipeline/__init__.py
mmir/pipeline/interceptor.py
mmir/pipeline/pipeline.py
mmir/stereo/__init__.py
mmir/stereo/disparity_map_calculator.py
mmir/stereo/disparity_transfer.py
mmir/stereo/sgbm_disparity_map_calculator.py
mmir-0.2.0.dist-info/METADATA
mmir-0.2.0.dist-info/RECORD
mmir-0.2.0.dist-info/WHEEL
mmir-0.2.0.dist-info/top_level.txt
