Metadata-Version: 2.1
Name: mmir
Version: 0.2.0
Summary: A package for aiding you in the quest of registering VIS and LWIR images
Home-page: https://bitbucket.org/_alexandrukis/pyreg/src/master/
Author: Alexandru Kis
Author-email: alexandrukis1618033@gmail.com
License: UNKNOWN
Platform: UNKNOWN
Classifier: Programming Language :: Python :: 3
Classifier: License :: OSI Approved :: BSD License
Classifier: Operating System :: OS Independent
Requires-Dist: bresenham (==0.2)
Requires-Dist: dataclasses (==0.6)
Requires-Dist: funcy (==1.10.2)
Requires-Dist: joblib (==0.12.0)
Requires-Dist: multipledispatch (==0.5.0)
Requires-Dist: numpy (==1.14.5)
Requires-Dist: opencv-contrib-python (==3.4.1.15)
Requires-Dist: scikit-image (==0.14.0)
Requires-Dist: scipy (==1.1.0)
